numpy_flint-0.3.4.dist-info/copying.lesser.md
numpy_flint-0.3.4.dist-info/copying.md
numpy_flint-0.3.4.dist-info/RECORD
numpy_flint-0.3.4.dist-info/top_level.txt
numpy_flint-0.3.4.dist-info/METADATA
numpy_flint-0.3.4.dist-info/WHEEL
flint/numpy_flint.cpython-39-x86_64-linux-gnu.so
flint/numpy_flint.c
flint/flint.h
flint/numpy_flint.h
flint/__init__.py
