Metadata-Version: 2.1
Name: numpy-flint
Version: 0.3.4
Summary: Add a rounded floating point interval (flint) dtype to NumPy
Author-email: Jef Wagner <jefwagner@gmail.com>
Project-URL: Homepage, https://jefwagner.github.io/flint
Project-URL: Bug Tracker, https://github.com/jefwagner/numpy-flint/issues
Requires-Python: >=3.7
License-File: copying.lesser.md
License-File: copying.md
Requires-Dist: numpy >=1.14.5
